vmail_manager/__init__.py
vmail_manager/alias.py
vmail_manager/config_default.yaml
vmail_manager/db.py
vmail_manager/domain.py
vmail_manager/helpers.py
vmail_manager/user.py
vmail_manager-0.2.1.dist-info/entry_points.txt
vmail_manager-0.2.1.dist-info/LICENSE
vmail_manager-0.2.1.dist-info/WHEEL
vmail_manager-0.2.1.dist-info/METADATA
vmail_manager-0.2.1.dist-info/RECORD
