Metadata-Version: 2.1
Name: vmail-manager
Version: 0.2.1
Summary: Handy cli interface to manage an vmail-sql-db.
License: MIT
Author: Dominik Rimpf
Author-email: dev@d-rimpf.de
Requires-Python: >=3.7,<4.0
Classifier: Development Status :: 3 - Alpha
Classifier: License :: OSI Approved :: MIT License
Classifier: Operating System :: OS Independent
Classifier: Programming Language :: Python :: 3
Classifier: Programming Language :: Python :: 3.6
Classifier: Programming Language :: Python :: 3.7
Classifier: Programming Language :: Python :: 3.8
Requires-Dist: argon2_cffi (>=19.2.0,<20.0.0)
Requires-Dist: click (>=7.0,<8.0)
Requires-Dist: confuse (>=1.0.0,<2.0.0)
Requires-Dist: sqlalchemy[pymysql] (>=1.3.13,<2.0.0)
Requires-Dist: tabulate (>=0.8.6,<0.9.0)
